[
  {
    "time": "Antes del tiempo",
    "title": "En el principio era el Verbo",
    "references": "Juan 1"
  },
  {
    "time": "Antes del 4000 a. C.",
    "title": "La creación",
    "references": "Génesis 1"
  },
  {
    "time": "Antes del 4000 a. C.",
    "title": "El jardín del Edén",
    "references": "Génesis 2"
  },
  {
    "time": "Antes del 4000 a. C.",
    "title": "La caída del hombre",
    "references": "Génesis 3"
  },
  {
    "time": "Antes del 3000 a. C.",
    "title": "Caín mata a Abel",
    "references": "Génesis 4"
  },
  {
    "time": "Antes del 3000 a. C.",
    "title": "De Adán a Noé",
    "references": "Génesis 5"
  },
  {
    "time": "Antes del 2500 a. C.",
    "title": "La maldad provoca la ira de Dios",
    "references": "Génesis 6"
  },
  {
    "time": "Antes del 2500 a. C.",
    "title": "El gran diluvio",
    "references": "Génesis 7"
  },
  {
    "time": "Antes del 2500 a. C.",
    "title": "La inundación disminuye",
    "references": "Génesis 8"
  },
  {
    "time": "Antes del 2500 a. C.",
    "title": "Pacto del Arcoiris",
    "references": "Génesis 9"
  },
  {
    "time": "Antes del 2500 a. C.",
    "title": "Sem, Cam y Jafet",
    "references": "Génesis 10"
  },
  {
    "time": "Antes del 2100 a. C.",
    "title": "El sufrimiento y la fe de Job",
    "references": "Trabajo 1 - 42"
  },
  {
    "time": "Antes del 2100 a. C.",
    "title": "La Torre de Babel",
    "references": "Génesis 11"
  },
  {
    "time": "2091 a. C.",
    "title": "Dios envía a Abram a Egipto",
    "references": "Génesis 12"
  },
  {
    "time": "2090 a. C.",
    "title": "La hambruna en Canaán",
    "references": "Génesis 12:10"
  },
  {
    "time": "2085 a. C.",
    "title": "Abram y Lot se separan",
    "references": "Génesis 13"
  },
  {
    "time": "2085 a. C.",
    "title": "A Abram se le prometió una descendencia numerosa",
    "references": "Génesis 13:14"
  },
  {
    "time": "2084 a. C.",
    "title": "Abram rescata a Lot",
    "references": "Génesis 14"
  },
  {
    "time": "2081 a. C.",
    "title": "El pacto de Dios con Abram",
    "references": "Génesis 15"
  },
  {
    "time": "2081 a. C.",
    "title": "Sarai y Agar",
    "references": "Génesis 16"
  },
  {
    "time": "2080 a. C.",
    "title": "Nació Ismael",
    "references": "Génesis 16:15"
  },
  {
    "time": "2067 a. C.",
    "title": "El pacto de la circuncisión",
    "references": "Génesis 17"
  },
  {
    "time": "2067 a. C.",
    "title": "Dios promete el nacimiento de Isaac",
    "references": "Génesis 18"
  },
  {
    "time": "2067 a. C.",
    "title": "La destrucción de Sodoma",
    "references": "Génesis 19"
  },
  {
    "time": "2067 a. C.",
    "title": "Abraham, Sara y Abimelec",
    "references": "Génesis 20"
  },
  {
    "time": "2066 a. C.",
    "title": "Nació Isaac",
    "references": "Génesis 21"
  },
  {
    "time": "2064 a. C.",
    "title": "Agar e Ismael son despedidos",
    "references": "Génesis 21:8"
  },
  {
    "time": "2057 a. C.",
    "title": "El tratado de Beersheba",
    "references": "Génesis 21:22"
  },
  {
    "time": "2054 a. C.",
    "title": "La ofrenda de Isaac",
    "references": "Génesis 22"
  },
  {
    "time": "2030 a. C.",
    "title": "Muerte y entierro de Sara",
    "references": "Génesis 23"
  },
  {
    "time": "2026 a. C.",
    "title": "Isaac se casa con Rebeca",
    "references": "Génesis 24"
  },
  {
    "time": "2006 a. C.",
    "title": "Nacimiento de Jacob y Esaú",
    "references": "Génesis 25"
  },
  {
    "time": "1991 a. C.",
    "title": "Muerte de Abraham",
    "references": "Génesis 25:5"
  },
  {
    "time": "1978 a. C.",
    "title": "Esaú vende su primogenitura",
    "references": "Génesis 25:29"
  },
  {
    "time": "1977 a. C.",
    "title": "Isaac y Abimelec",
    "references": "Génesis 26"
  },
  {
    "time": "1929 a. C.",
    "title": "Jacob recibe la bendición de Isaac",
    "references": "Génesis 27"
  },
  {
    "time": "1928 a. C.",
    "title": "Jacob huye hacia Labán",
    "references": "Génesis 28"
  },
  {
    "time": "1928 a. C.",
    "title": "La visión de Jacob de una escalera",
    "references": "Génesis 28:10"
  },
  {
    "time": "1928 a. C.",
    "title": "Jacob sirve a Labán",
    "references": "Génesis 29"
  },
  {
    "time": "1921 a. C.",
    "title": "Jacob se casa con Raquel",
    "references": "Génesis 29:28"
  },
  {
    "time": "1921 a. C.",
    "title": "Jacob y sus hijos",
    "references": "Génesis 30"
  },
  {
    "time": "1916 a. C.",
    "title": "Raquel lleva a José",
    "references": "Génesis 30:22"
  },
  {
    "time": "1908 a. C.",
    "title": "Jacob parte hacia Canaán",
    "references": "Génesis 31"
  },
  {
    "time": "1906 a. C.",
    "title": "Jacob lucha con Dios",
    "references": "Génesis 32"
  },
  {
    "time": "1906 a. C.",
    "title": "Jacob se encuentra con Esaú",
    "references": "Génesis 33"
  },
  {
    "time": "1906 a. C.",
    "title": "Jacob se establece en Siquem",
    "references": "Génesis 33:18"
  },
  {
    "time": "1906 a. C.",
    "title": "Siquem profana a Dina",
    "references": "Génesis 34"
  },
  {
    "time": "1906 a. C.",
    "title": "Jacob regresa a Betel",
    "references": "Génesis 35"
  },
  {
    "time": "1906 a. C.",
    "title": "Jacob llamado Israel",
    "references": "Génesis 35:10"
  },
  {
    "time": "1906 a. C.",
    "title": "Descendientes de Esaú",
    "references": "Génesis 36"
  },
  {
    "time": "1903 a. C.",
    "title": "Rachel muere",
    "references": "Génesis 35:18"
  },
  {
    "time": "1898 a. C.",
    "title": "Los sueños y la traición de José",
    "references": "Génesis 37"
  },
  {
    "time": "1898 a. C.",
    "title": "José vendido como esclavo",
    "references": "Génesis 37:25"
  },
  {
    "time": "1898 a. C.",
    "title": "Tamar engaña a Judá",
    "references": "Génesis 38"
  },
  {
    "time": "1898 a. C.",
    "title": "José prospera bajo el mando de Potifar",
    "references": "Génesis 39"
  },
  {
    "time": "1889 a. C.",
    "title": "La esposa de Potifar acusa a José",
    "references": "Génesis 39:7"
  },
  {
    "time": "1889 a. C.",
    "title": "José encarcelado",
    "references": "Génesis 39:20"
  },
  {
    "time": "1887 a. C.",
    "title": "El copero y los sueños del panadero",
    "references": "Génesis 40"
  },
  {
    "time": "1886 a. C.",
    "title": "José interpreta los sueños del faraón",
    "references": "Génesis 41"
  },
  {
    "time": "1886 a. C.",
    "title": "José puesto a cargo",
    "references": "Génesis 41:33"
  },
  {
    "time": "1886 a. C.",
    "title": "Comienzan siete años de abundancia",
    "references": "Génesis 41:47"
  },
  {
    "time": "1875 a. C.",
    "title": "Comienza la hambruna",
    "references": "Génesis 41:53"
  },
  {
    "time": "1875 a. C.",
    "title": "Los hermanos de José enviados a Egipto",
    "references": "Génesis 42"
  },
  {
    "time": "1875 a. C.",
    "title": "Simeón detenido por José",
    "references": "Génesis 42:24"
  },
  {
    "time": "1875 a. C.",
    "title": "El regreso con Benjamin",
    "references": "Génesis 43"
  },
  {
    "time": "1875 a. C.",
    "title": "Benjamín y la copa de plata",
    "references": "Génesis 44"
  },
  {
    "time": "1875 a. C.",
    "title": "José revela su identidad",
    "references": "Génesis 45"
  },
  {
    "time": "1875 a. C.",
    "title": "José manda a buscar a Jacob",
    "references": "Génesis 45:9"
  },
  {
    "time": "1875 a. C.",
    "title": "Jacob y su familia viajan a Egipto",
    "references": "Génesis 46"
  },
  {
    "time": "1875 a. C.",
    "title": "De Jacob a Gosén",
    "references": "Génesis 47"
  },
  {
    "time": "1859 a. C.",
    "title": "La enfermedad de Jacob",
    "references": "Génesis 48"
  },
  {
    "time": "1859 a. C.",
    "title": "La bendición y la muerte de Jacob",
    "references": "Génesis 49"
  },
  {
    "time": "1859 a. C.",
    "title": "El entierro de Jacob",
    "references": "Génesis 50"
  },
  {
    "time": "1806 a. C.",
    "title": "La muerte de José",
    "references": "Génesis 50:26"
  },
  {
    "time": "1800 a. C.",
    "title": "La familia de Jacob se queda en Egipto",
    "references": "Éxodo 1"
  },
  {
    "time": "1700 a. C.",
    "title": "Los israelitas se multiplican en Egipto",
    "references": "Éxodo 1:6"
  },
  {
    "time": "1600 a. C.",
    "title": "Los israelitas oprimidos por el nuevo rey",
    "references": "Éxodo 1:8"
  },
  {
    "time": "1539 a. C.",
    "title": "La orden del faraón de matar a los primogénitos",
    "references": "Éxodo 1:22"
  },
  {
    "time": "1525 a. C.",
    "title": "El nacimiento y la adopción de Moisés",
    "references": "Éxodo 2"
  },
  {
    "time": "1486 a. C.",
    "title": "Moisés huye a Madián",
    "references": "Éxodo 2:11"
  },
  {
    "time": "1446 a. C.",
    "title": "Los israelitas gimen en la esclavitud",
    "references": "Éxodo 2:23"
  },
  {
    "time": "1446 a. C.",
    "title": "Moisés enviado a liberar a Israel",
    "references": "Éxodo 3 - 6"
  },
  {
    "time": "1446 a. C.",
    "title": "Las diez plagas de Egipto",
    "references": "Éxodo 7 - 12"
  },
  {
    "time": "1446 a. C.",
    "title": "El éxodo comienza",
    "references": "Éxodo 13 - 18"
  },
  {
    "time": "1446 a. C.",
    "title": "Los israelitas en el monte Sinaí",
    "references": "Éxodo 19"
  },
  {
    "time": "1446 a. C.",
    "title": "Moisés recibe los mandamientos",
    "references": "Éxodo 20"
  },
  {
    "time": "1446 a. C.",
    "title": "Moisés recibe la ley",
    "references": "Éxodo 21 - 24"
  },
  {
    "time": "1446 a. C.",
    "title": "Preparaciones para el Tabernáculo",
    "references": "Éxodo 25 - 31"
  },
  {
    "time": "1446 a. C.",
    "title": "El becerro de oro y la ira de Moisés",
    "references": "Éxodo 32"
  },
  {
    "time": "1446 a. C.",
    "title": "El viaje se reanuda",
    "references": "Éxodo 33 - 39"
  },
  {
    "time": "1445 a. C.",
    "title": "El Tabernáculo está erigido y lleno",
    "references": "Éxodo 40"
  },
  {
    "time": "1445 a. C.",
    "title": "Leyes para los sacrificios y ofrendas",
    "references": "Levítico 1 - 7"
  },
  {
    "time": "1445 a. C.",
    "title": "Aarón y sus hijos consagrados",
    "references": "Levítico 8, 9"
  },
  {
    "time": "1445 a. C.",
    "title": "El pecado de Nadab y Abiú",
    "references": "Levítico 10"
  },
  {
    "time": "1445 a. C.",
    "title": "Leyes de pureza",
    "references": "Levítico 11 - 19"
  },
  {
    "time": "1445 a. C.",
    "title": "Castigos y reglamentos",
    "references": "Levítico 20 - 22"
  },
  {
    "time": "1445 a. C.",
    "title": "Fiestas y Jubileo",
    "references": "Levítico 23"
  },
  {
    "time": "1445 a. C.",
    "title": "Censo, tribus y deberes",
    "references": "Números 1 - 6"
  },
  {
    "time": "1445 a. C.",
    "title": "Dedicación del Tabernáculo",
    "references": "Números 7 - 10"
  },
  {
    "time": "1445 a. C.",
    "title": "El pueblo se queja",
    "references": "Números 11, 12"
  },
  {
    "time": "1445 a. C.",
    "title": "Los doce espías",
    "references": "Números 13"
  },
  {
    "time": "1445 a. C.",
    "title": "La gente murmura ante el informe de los espías",
    "references": "Números 14, 15"
  },
  {
    "time": "1426 a. C.",
    "title": "La rebelión de Coré",
    "references": "Números 16"
  },
  {
    "time": "1426 a. C.",
    "title": "Cogollos de Aaron",
    "references": "Números 17"
  },
  {
    "time": "1426 a. C.",
    "title": "Sacerdotes, Vaquilla Roja, Limpieza",
    "references": "Números 18, 19"
  },
  {
    "time": "1407 a. C.",
    "title": "Agua de la roca en Meribah",
    "references": "Números 20"
  },
  {
    "time": "1407 a. C.",
    "title": "La muerte de Aarón",
    "references": "Números 20:22"
  },
  {
    "time": "1407 a. C.",
    "title": "La serpiente de bronce",
    "references": "Números 21"
  },
  {
    "time": "1407 a. C.",
    "title": "Balaam y el ángel",
    "references": "Números 22 - 25"
  },
  {
    "time": "1407 a. C.",
    "title": "El segundo censo",
    "references": "Números 26"
  },
  {
    "time": "1407 a. C.",
    "title": "Las hijas de Zelofehad",
    "references": "Números 27"
  },
  {
    "time": "1407 a. C.",
    "title": "Josué elegido para suceder a Moisés",
    "references": "Números 27:18"
  },
  {
    "time": "1407 a. C.",
    "title": "Sacrificios especiales y días santos",
    "references": "Números 28, 29"
  },
  {
    "time": "1407 a. C.",
    "title": "Votos de mujeres",
    "references": "Números 30"
  },
  {
    "time": "1407 a. C.",
    "title": "Conquista de Madián",
    "references": "Números 31"
  },
  {
    "time": "1407 a. C.",
    "title": "División de Transjordania",
    "references": "Números 32"
  },
  {
    "time": "1407 a. C.",
    "title": "Resumen del viaje de Israel",
    "references": "Números 33"
  },
  {
    "time": "1407 a. C.",
    "title": "Reparto de Canaán",
    "references": "Números 34"
  },
  {
    "time": "1407 a. C.",
    "title": "Fronteras y ciudades de refugio",
    "references": "Números 35"
  },
  {
    "time": "1407 a. C.",
    "title": "Las hijas de Zelofehad se casan",
    "references": "Números 36"
  },
  {
    "time": "1407 a. C.",
    "title": "Salmo de Moisés",
    "references": "Salmo 90"
  },
  {
    "time": "1407 a. C.",
    "title": "Resumen de la historia de Israel según Moisés",
    "references": "Deuteronomio 1 - 4"
  },
  {
    "time": "1406 a. C.",
    "title": "Recapitulación de la Ley",
    "references": "Deuteronomio 4:44-31"
  },
  {
    "time": "1406 a. C.",
    "title": "El cántico de Moisés",
    "references": "Deuteronomio 32"
  },
  {
    "time": "1406 a. C.",
    "title": "Moisés bendice a las doce tribus",
    "references": "Deuteronomio 32:48"
  },
  {
    "time": "1406 a. C.",
    "title": "Bendiciones de Moisés",
    "references": "Deuteronomio 33"
  },
  {
    "time": "1406 a. C.",
    "title": "La muerte de Moisés",
    "references": "Deuteronomio 34"
  },
  {
    "time": "1406 a. C.",
    "title": "Dios comisiona a Josué",
    "references": "Josué 1"
  },
  {
    "time": "1406 a. C.",
    "title": "Rahab da la bienvenida a los espías",
    "references": "Josué 2"
  },
  {
    "time": "1406 a. C.",
    "title": "Los israelitas cruzan el Jordán",
    "references": "Josué 3 - 5"
  },
  {
    "time": "1406 a. C.",
    "title": "Conquista de Jericó y Hai",
    "references": "Josué 6 - 8"
  },
  {
    "time": "1405 a. C.",
    "title": "Los reyes se unen contra Israel",
    "references": "Josué 9"
  },
  {
    "time": "1405 a. C.",
    "title": "El sol se detiene",
    "references": "Josué 10"
  },
  {
    "time": "1405 a. C.",
    "title": "El norte de Palestina derrotado",
    "references": "Josué 11, 12"
  },
  {
    "time": "1399 a. C.",
    "title": "Tierra repartida entre las tribus",
    "references": "Josué 13 - 22"
  },
  {
    "time": "1375 a. C.",
    "title": "Discurso de despedida de Josué",
    "references": "Josué 23, 24"
  },
  {
    "time": "1375 a. C.",
    "title": "La idolatría de Miqueas",
    "references": "Jueces 17"
  },
  {
    "time": "1375 a. C.",
    "title": "Los danitas se establecen en Lais y toman los ídolos de Micaía",
    "references": "Jueces 18"
  },
  {
    "time": "1375 a. C.",
    "title": "La concubina de un levita degradada",
    "references": "Jueces 19"
  },
  {
    "time": "1375 a. C.",
    "title": "Los israelitas derrotan a los benjamitas",
    "references": "Jueces 20"
  },
  {
    "time": "1375 a. C.",
    "title": "Esposas para los benjamitas",
    "references": "Jueces 21"
  },
  {
    "time": "1374 a. C.",
    "title": "Los israelitas capturan Jerusalén y Hebrón",
    "references": "Jueces 1"
  },
  {
    "time": "1374 a. C.",
    "title": "Israel reprendido y derrotado",
    "references": "Jueces 2"
  },
  {
    "time": "1374 a. C.",
    "title": "La idolatría y la servidumbre de Israel; Otoniel",
    "references": "Jueces 3"
  },
  {
    "time": "1334 a. C.",
    "title": "Eglón",
    "references": "Jueces 3:12"
  },
  {
    "time": "1316 a. C.",
    "title": "Ehud",
    "references": "Jueces 3:15"
  },
  {
    "time": "1235 a. C.",
    "title": "Débora y Barac",
    "references": "Jueces 4"
  },
  {
    "time": "1235 a. C.",
    "title": "El cántico de Débora y Barac",
    "references": "Jueces 5"
  },
  {
    "time": "1169 a. C.",
    "title": "Gedeón y los madianitas",
    "references": "Jueces 6 - 8"
  },
  {
    "time": "1140 a. C.",
    "title": "Noemí, Rut y Booz",
    "references": "Rut 1 - 4"
  },
  {
    "time": "1129 a. C.",
    "title": "Abimelec conspira para convertirse en rey",
    "references": "Jueces 9"
  },
  {
    "time": "1126 a. C.",
    "title": "Complot contra Abimelec",
    "references": "Jueces 9:22"
  },
  {
    "time": "1126 a. C.",
    "title": "Abimelec es asesinado",
    "references": "Jueces 9:50"
  },
  {
    "time": "1118 a. C.",
    "title": "Tola, Jair",
    "references": "Jueces 10"
  },
  {
    "time": "1100 a. C.",
    "title": "Nacimiento de Samuel",
    "references": "1 Samuel 1"
  },
  {
    "time": "1100 a. C.",
    "title": "La canción de Hannah",
    "references": "1 Samuel 2"
  },
  {
    "time": "1097 a. C.",
    "title": "El pacto de Jefté con los galaaditas",
    "references": "Jueces 11"
  },
  {
    "time": "1090 a. C.",
    "title": "Jefté, Efraín, Ibzán, Elón, Abdón",
    "references": "Jueces 12"
  },
  {
    "time": "1090 a. C.",
    "title": "Israel oprimido por los filisteos",
    "references": "Jueces 13"
  },
  {
    "time": "1075 a. C.",
    "title": "Las bodas de Sansón y el enigma",
    "references": "Jueces 14"
  },
  {
    "time": "1075 a. C.",
    "title": "Sansón quema las cosechas de los filisteos",
    "references": "Jueces 15"
  },
  {
    "time": "1075 a. C.",
    "title": "Sansón y Dalila",
    "references": "Jueces 16"
  },
  {
    "time": "1070 a. C.",
    "title": "Batalla de Shiloh",
    "references": "1 Samuel 3"
  },
  {
    "time": "1070 a. C.",
    "title": "Los filisteos toman el arca",
    "references": "1 Samuel 4, 5"
  },
  {
    "time": "1070 a. C.",
    "title": "Los filisteos devuelven el arca a Israel",
    "references": "1 Samuel 6"
  },
  {
    "time": "1070 a. C.",
    "title": "El Arca fue llevada a la casa de Abinadab",
    "references": "1 Samuel 7"
  },
  {
    "time": "1050 a. C.",
    "title": "Los israelitas se arrepienten en Mizpa",
    "references": "1 Samuel 7:3"
  },
  {
    "time": "1043 a. C.",
    "title": "Saúl se convierte en rey",
    "references": "1 Samuel 8 - 10"
  },
  {
    "time": "1042 a. C.",
    "title": "Saúl derrota a los amonitas",
    "references": "1 Samuel 11, 12"
  },
  {
    "time": "1041 a. C.",
    "title": "La guerra de Saúl contra los filisteos",
    "references": "1 Samuel 13"
  },
  {
    "time": "1041 a. C.",
    "title": "La milagrosa victoria de Jonatán",
    "references": "1 Samuel 14"
  },
  {
    "time": "1028 a. C.",
    "title": "La desobediencia de Saúl y la reprensión de Samuel",
    "references": "1 Samuel 15"
  },
  {
    "time": "1024 a. C.",
    "title": "Samuel unge a David en Belén",
    "references": "1 Samuel 16"
  },
  {
    "time": "1024 a. C.",
    "title": "David mata a Goliat",
    "references": "1 Samuel 17"
  },
  {
    "time": "1015 a. C.",
    "title": "La amistad de Jonatán con David",
    "references": "1 Samuel 18"
  },
  {
    "time": "1014 a. C.",
    "title": "David protegido de Saúl",
    "references": "1 Samuel 19"
  },
  {
    "time": "1013 a. C.",
    "title": "El pacto entre David y Jonatán",
    "references": "1 Samuel 20"
  },
  {
    "time": "1013 a. C.",
    "title": "Salmo de liberación de David (1Sa 20)",
    "references": "Salmo 59"
  },
  {
    "time": "1012 a. C.",
    "title": "David en Nob y Gat",
    "references": "1 Samuel 21"
  },
  {
    "time": "1012 a. C.",
    "title": "Salmo de David huyendo de Saúl (1Sa 21)",
    "references": "Salmo 52"
  },
  {
    "time": "1012 a. C.",
    "title": "Salmo de David ante Ahimelec (1Sa 21)",
    "references": "Salmo 34"
  },
  {
    "time": "1011 a. C.",
    "title": "Salmo de David en Gat (1Sa 21)",
    "references": "Salmo 56"
  },
  {
    "time": "1011 a. C.",
    "title": "Saúl mata a los sacerdotes de Nob",
    "references": "1 Samuel 22"
  },
  {
    "time": "1011 a. C.",
    "title": "Los Salmos de David en la cueva (1Sa 22)",
    "references": "Salmos 57, 142"
  },
  {
    "time": "1011 a. C.",
    "title": "David huye de Saúl",
    "references": "1 Samuel 23"
  },
  {
    "time": "1011 a. C.",
    "title": "Salmo de David en Keila (1Sa 23)",
    "references": "Salmo 54"
  },
  {
    "time": "1011 a. C.",
    "title": "David perdona la vida a Saúl",
    "references": "1 Samuel 24"
  },
  {
    "time": "1011 a. C.",
    "title": "Samuel muere",
    "references": "1 Samuel 25"
  },
  {
    "time": "1011 a. C.",
    "title": "David perdona a Saúl por segunda vez",
    "references": "1 Samuel 26"
  },
  {
    "time": "1010 a. C.",
    "title": "David huye a los filisteos",
    "references": "1 Samuel 27"
  },
  {
    "time": "1010 a. C.",
    "title": "Saúl y la bruja de Endor",
    "references": "1 Samuel 28"
  },
  {
    "time": "1010 a. C.",
    "title": "Aquis despide a David",
    "references": "1 Samuel 29"
  },
  {
    "time": "1010 a. C.",
    "title": "David destruye a los amalecitas",
    "references": "1 Samuel 30"
  },
  {
    "time": "1010 a. C.",
    "title": "Saúl y sus hijos asesinados",
    "references": "1 Samuel 31"
  },
  {
    "time": "1010 a. C.",
    "title": "David llora por Saúl y Jonatán",
    "references": "2 Samuel 1"
  },
  {
    "time": "1010 a. C.",
    "title": "David nombrado rey sobre Judá",
    "references": "2 Samuel 2"
  },
  {
    "time": "1008 a. C.",
    "title": "Guerra civil entre Abner y Joab",
    "references": "2 Samuel 2:12"
  },
  {
    "time": "1006 a. C.",
    "title": "La Casa de David se fortalece",
    "references": "2 Samuel 3"
  },
  {
    "time": "1005 a. C.",
    "title": "Joab asesina a Abner",
    "references": "2 Samuel 3:22"
  },
  {
    "time": "1004 a. C.",
    "title": "El asesinato de Is-boset",
    "references": "2 Samuel 4"
  },
  {
    "time": "1003 a. C.",
    "title": "Genealogías de los israelitas",
    "references": "1 Crónicas 1 - 9"
  },
  {
    "time": "1003 a. C.",
    "title": "El derrocamiento y la derrota de Saúl",
    "references": "1 Crónicas 10"
  },
  {
    "time": "1003 a. C.",
    "title": "David reina sobre todo Israel",
    "references": "2 Samuel 5 , 1 Crónicas 11"
  },
  {
    "time": "1002 a. C.",
    "title": "El ejército de David crece",
    "references": "1 Crónicas 12"
  },
  {
    "time": "1000 a. C.",
    "title": "David trae el arca",
    "references": "1 Crónicas 13"
  },
  {
    "time": "1000 a. C.",
    "title": "La familia de David crece",
    "references": "1 Crónicas 14"
  },
  {
    "time": "1000 a. C.",
    "title": "El Arca es traída a Jerusalén",
    "references": "2 Samuel 6 , 1 Crónicas 15"
  },
  {
    "time": "1000 a. C.",
    "title": "David planea un templo",
    "references": "2 Samuel 7"
  },
  {
    "time": "998 a. C.",
    "title": "David derrota a los filisteos",
    "references": "2 Samuel 8"
  },
  {
    "time": "998 a. C.",
    "title": "Salmo de victoria de David (2Sa 8)",
    "references": "Salmo 60"
  },
  {
    "time": "998 a. C.",
    "title": "Salmo de Sión de David",
    "references": "Salmo 15"
  },
  {
    "time": "998 a. C.",
    "title": "Salmo de David de gloria a Dios",
    "references": "Salmo 24"
  },
  {
    "time": "998 a. C.",
    "title": "El sacrificio festivo de David",
    "references": "1 Crónicas 16"
  },
  {
    "time": "998 a. C.",
    "title": "Salmos de alabanza (1 Cr 16)",
    "references": "Salmos 96, 105, 106"
  },
  {
    "time": "997 a. C.",
    "title": "David se propone construir un templo",
    "references": "1 Crónicas 17"
  },
  {
    "time": "996 a. C.",
    "title": "David fortalece su reino",
    "references": "1 Crónicas 18"
  },
  {
    "time": "995 a. C.",
    "title": "David y Mefiboset",
    "references": "2 Samuel 9"
  },
  {
    "time": "995 a. C.",
    "title": "David derrota a Amón y Aram",
    "references": "2 Samuel 10 , 1 Crónicas 19"
  },
  {
    "time": "995 a. C.",
    "title": "La captura de Rabbah",
    "references": "1 Crónicas 20"
  },
  {
    "time": "993 a. C.",
    "title": "David y Betsabé",
    "references": "2 Samuel 11"
  },
  {
    "time": "991 a. C.",
    "title": "Nathan reprende a David",
    "references": "2 Samuel 12"
  },
  {
    "time": "991 a. C.",
    "title": "Salmo de arrepentimiento de David (2Sa 12)",
    "references": "Salmo 51"
  },
  {
    "time": "990 a. C.",
    "title": "Nace Salomón",
    "references": "2 Samuel 12:24"
  },
  {
    "time": "990 a. C.",
    "title": "Amnón y Tamar",
    "references": "2 Samuel 13"
  },
  {
    "time": "990 a. C.",
    "title": "Amnom asesinado por Absalón",
    "references": "2 Samuel 13:23"
  },
  {
    "time": "988 a. C.",
    "title": "La viuda de Tecoa",
    "references": "2 Samuel 14"
  },
  {
    "time": "980 a. C.",
    "title": "Absalón recordado",
    "references": "2 Samuel 14:21"
  },
  {
    "time": "979 a. C.",
    "title": "Salmos de David",
    "references": "Salmos 2 - 145 (Varios)"
  },
  {
    "time": "979 a. C.",
    "title": "Salmos de Coré",
    "references": "Salmos 42 - 44, 84, 85, 87, 88"
  },
  {
    "time": "979 a. C.",
    "title": "Salmos de Asaf",
    "references": "Salmo 50, 73, 75 - 78, 80 - 83, 89"
  },
  {
    "time": "979 a. C.",
    "title": "Salmos de autores desconocidos",
    "references": "Salmos 1 - 150 (Varios)"
  },
  {
    "time": "979 a. C.",
    "title": "David fuerza un censo",
    "references": "1 Crónicas 21"
  },
  {
    "time": "979 a. C.",
    "title": "Preparación para la construcción del Templo",
    "references": "1 Crónicas 22"
  },
  {
    "time": "979 a. C.",
    "title": "Preparación del sacerdocio",
    "references": "1 Crónicas 23"
  },
  {
    "time": "979 a. C.",
    "title": "Divisiones de los levitas",
    "references": "1 Crónicas 24"
  },
  {
    "time": "979 a. C.",
    "title": "Preparación de los cantores del santuario",
    "references": "1 Crónicas 25"
  },
  {
    "time": "979 a. C.",
    "title": "Preparación de porteros, tesoreros",
    "references": "1 Crónicas 26"
  },
  {
    "time": "979 a. C.",
    "title": "Preparación del gobierno",
    "references": "1 Crónicas 27"
  },
  {
    "time": "976 a. C.",
    "title": "La conspiración de Absalón",
    "references": "2 Samuel 15"
  },
  {
    "time": "976 a. C.",
    "title": "David huye de Jerusalén",
    "references": "2 Samuel 15:13"
  },
  {
    "time": "972 a. C.",
    "title": "David y Ziba, Simei",
    "references": "2 Samuel 16"
  },
  {
    "time": "972 a. C.",
    "title": "Shimei maldice a David",
    "references": "2 Samuel 16:5"
  },
  {
    "time": "972 a. C.",
    "title": "Salmo de David sobre su sed de Dios (2Sa 16)",
    "references": "Salmo 63"
  },
  {
    "time": "972 a. C.",
    "title": "La advertencia de Husai salva a David",
    "references": "2 Samuel 17"
  },
  {
    "time": "972 a. C.",
    "title": "Salmos de liberación de David (2Sa 17)",
    "references": "Salmos 41, 55"
  },
  {
    "time": "972 a. C.",
    "title": "Absalón asesinado por Joab",
    "references": "2 Samuel 18"
  },
  {
    "time": "972 a. C.",
    "title": "Joab consuela a David",
    "references": "2 Samuel 19"
  },
  {
    "time": "972 a. C.",
    "title": "Seba se rebela contra David",
    "references": "2 Samuel 20"
  },
  {
    "time": "970 a. C.",
    "title": "Los gabaonitas se vengaron",
    "references": "2 Samuel 21"
  },
  {
    "time": "970 a. C.",
    "title": "El canto de liberación de David",
    "references": "2 Samuel 22"
  },
  {
    "time": "970 a. C.",
    "title": "La última canción de David",
    "references": "2 Samuel 23"
  },
  {
    "time": "970 a. C.",
    "title": "Salmo de David sobre la firmeza (2Sa 23)",
    "references": "Salmo 108"
  },
  {
    "time": "970 a. C.",
    "title": "David cuenta a los hombres combatientes",
    "references": "2 Samuel 24"
  },
  {
    "time": "970 a. C.",
    "title": "Los últimos días de David",
    "references": "1 Crónicas 28, 29 , 1 Reyes 1, 2"
  },
  {
    "time": "970 a. C.",
    "title": "Salmo de salvación de David (1 R 2)",
    "references": "Salmo 37"
  },
  {
    "time": "967 a. C.",
    "title": "Salmo de Salomón (2 Crónicas 1)",
    "references": "Salmo 72"
  },
  {
    "time": "967 a. C.",
    "title": "Salomón pide sabiduría",
    "references": "2 Crónicas 1 , 1 Reyes 3"
  },
  {
    "time": "967 a. C.",
    "title": "Salmo de Coré (1Re 3)",
    "references": "Salmo 45"
  },
  {
    "time": "967 a. C.",
    "title": "La sabiduría de Salomón",
    "references": "1 Reyes 4"
  },
  {
    "time": "967 a. C.",
    "title": "Los preparativos de Salomón para el templo",
    "references": "1 Reyes 5"
  },
  {
    "time": "966 a. C.",
    "title": "La construcción del Templo de Salomón",
    "references": "1 Reyes 6"
  },
  {
    "time": "966 a. C.",
    "title": "La construcción del palacio de Salomón",
    "references": "1 Reyes 7"
  },
  {
    "time": "966 a. C.",
    "title": "El Arca Traída al Templo",
    "references": "1 Reyes 8"
  },
  {
    "time": "966 a. C.",
    "title": "El pacto de Dios con Salomón",
    "references": "1 Reyes 9"
  },
  {
    "time": "966 a. C.",
    "title": "Salomón prepara un templo y un palacio",
    "references": "2 Crónicas 2"
  },
  {
    "time": "966 a. C.",
    "title": "Salomón construye el templo en Jerusalén",
    "references": "2 Crónicas 3"
  },
  {
    "time": "966 a. C.",
    "title": "Mobiliario del templo",
    "references": "2 Crónicas 4"
  },
  {
    "time": "959 a. C.",
    "title": "El Arca fue traída al Templo",
    "references": "2 Crónicas 5"
  },
  {
    "time": "959 a. C.",
    "title": "Oración de Salomón para la dedicación del templo",
    "references": "2 Crónicas 6"
  },
  {
    "time": "959 a. C.",
    "title": "La gloria de Dios en el templo",
    "references": "2 Crónicas 7"
  },
  {
    "time": "959 a. C.",
    "title": "Salmos de Salomón (2 Crónicas 7)",
    "references": "Salmos 135, 136"
  },
  {
    "time": "959 a. C.",
    "title": "Los edificios de Salomón",
    "references": "2 Crónicas 8"
  },
  {
    "time": "950 a. C.",
    "title": "Salmo de bendición de Salomón",
    "references": "Salmo 127"
  },
  {
    "time": "950 a. C.",
    "title": "Los Proverbios de Salomón",
    "references": "Proverbios 1 - 29"
  },
  {
    "time": "950 a. C.",
    "title": "Las palabras de Agur",
    "references": "Proverbios 30"
  },
  {
    "time": "950 a. C.",
    "title": "Proverbio del rey Lemuel",
    "references": "Proverbios 31"
  },
  {
    "time": "950 a. C.",
    "title": "El Cantar de los Cantares de Salomón",
    "references": "Canciones 1 - 8"
  },
  {
    "time": "946 a. C.",
    "title": "Regalos mutuos de Salomón e Hiran",
    "references": "1 Reyes 9:10"
  },
  {
    "time": "946 a. C.",
    "title": "La reina de Saba visita a Salomón",
    "references": "1 Reyes 10 , 2 Crónicas 9"
  },
  {
    "time": "939 a. C.",
    "title": "Las esposas de Salomón y la idolatría",
    "references": "1 Reyes 11"
  },
  {
    "time": "937 a. C.",
    "title": "Eclesiastés Palabras del Predicador",
    "references": "Eclesiastés 1 - 12"
  },
  {
    "time": "931 a. C.",
    "title": "La muerte de Salomón",
    "references": "1 Reyes 11:40"
  },
  {
    "time": "931 a. C.",
    "title": "El reino está dividido",
    "references": "1 Reyes 12, 13"
  },
  {
    "time": "930 a. C.",
    "title": "Los israelitas se rebelan contra Roboam",
    "references": "2 Crónicas 10"
  },
  {
    "time": "930 a. C.",
    "title": "El reinado de Roboam sobre Judá",
    "references": "2 Crónicas 11"
  },
  {
    "time": "927 a. C.",
    "title": "El pecado de Roboam",
    "references": "2 Crónicas 12"
  },
  {
    "time": "925 a. C.",
    "title": "Las profecías de Ahías contra Jeroboam",
    "references": "1 Reyes 14"
  },
  {
    "time": "913 a. C.",
    "title": "El reinado perverso de Roboam",
    "references": "1 Reyes 14:21"
  },
  {
    "time": "913 a. C.",
    "title": "El reinado malvado de Abiam",
    "references": "1 Reyes 15"
  },
  {
    "time": "913 a. C.",
    "title": "Guerra civil contra Jeroboam",
    "references": "2 Crónicas 13"
  },
  {
    "time": "913 a. C.",
    "title": "Asa destruye la idolatría",
    "references": "2 Crónicas 14"
  },
  {
    "time": "909 a. C.",
    "title": "La profecía de Jehú contra Baasa",
    "references": "1 Reyes 16"
  },
  {
    "time": "895 a. C.",
    "title": "Las reformas de Asa",
    "references": "2 Crónicas 15"
  },
  {
    "time": "894 a. C.",
    "title": "La reprimenda de Hanani",
    "references": "2 Crónicas 16"
  },
  {
    "time": "886 a. C.",
    "title": "Ela, Zimri, Omri",
    "references": "1 Reyes 16:5"
  },
  {
    "time": "874 a. C.",
    "title": "El reinado malvado de Acab",
    "references": "1 Reyes 16:27"
  },
  {
    "time": "869 a. C.",
    "title": "Josafat sucede a Asa",
    "references": "2 Crónicas 17"
  },
  {
    "time": "863 a. C.",
    "title": "Elías ora por la sequía",
    "references": "1 Reyes 17"
  },
  {
    "time": "863 a. C.",
    "title": "Elijah alimentado por cuervos",
    "references": "1 Reyes 17:3"
  },
  {
    "time": "863 a. C.",
    "title": "La viuda de Sarepta",
    "references": "1 Reyes 17:7"
  },
  {
    "time": "863 a. C.",
    "title": "Elías en el monte Carmelo",
    "references": "1 Reyes 18"
  },
  {
    "time": "858 a. C.",
    "title": "Elías huye de Jezabel",
    "references": "1 Reyes 19"
  },
  {
    "time": "858 a. C.",
    "title": "Eliseo llamado",
    "references": "1 Reyes 19:19"
  },
  {
    "time": "857 a. C.",
    "title": "Ben-Hadad ataca Samaria",
    "references": "1 Reyes 20"
  },
  {
    "time": "857 a. C.",
    "title": "Acab derrota a Ben-Hadad",
    "references": "1 Reyes 20:14"
  },
  {
    "time": "855 a. C.",
    "title": "Acab toma la viña de Nabot",
    "references": "1 Reyes 21"
  },
  {
    "time": "853 a. C.",
    "title": "Israel y Judá contra Siria",
    "references": "1 Reyes 22"
  },
  {
    "time": "853 a. C.",
    "title": "La visión de Abdías",
    "references": "Abdías 1"
  },
  {
    "time": "853 a. C.",
    "title": "Josafat se alía con Acab",
    "references": "2 Crónicas 18"
  },
  {
    "time": "853 a. C.",
    "title": "Las obras de Jehosafat",
    "references": "2 Crónicas 19"
  },
  {
    "time": "853 a. C.",
    "title": "Guerra con Amón y Moab",
    "references": "2 Crónicas 20"
  },
  {
    "time": "852 a. C.",
    "title": "El reinado perverso de Joram en Judá",
    "references": "2 Crónicas 21"
  },
  {
    "time": "852 a. C.",
    "title": "Rebeldes de Moab",
    "references": "2 Reyes 1"
  },
  {
    "time": "851 a. C.",
    "title": "Elías llevado al cielo",
    "references": "2 Reyes 2"
  },
  {
    "time": "851 a. C.",
    "title": "Eliseo sucede a Elías",
    "references": "2 Reyes 2:12"
  },
  {
    "time": "850 a. C.",
    "title": "Joram se enfrenta a la rebelión de Moab",
    "references": "2 Reyes 3"
  },
  {
    "time": "849 a. C.",
    "title": "El aceite de la viuda",
    "references": "2 Reyes 4"
  },
  {
    "time": "849 a. C.",
    "title": "Eliseo cría al niño sunamita",
    "references": "2 Reyes 4:8"
  },
  {
    "time": "849 a. C.",
    "title": "La curación de Naamán",
    "references": "2 Reyes 5"
  },
  {
    "time": "848 a. C.",
    "title": "Eliseo hace flotar un hacha",
    "references": "2 Reyes 6"
  },
  {
    "time": "848 a. C.",
    "title": "Eliseo promete abundancia en Samaria",
    "references": "2 Reyes 7"
  },
  {
    "time": "847 a. C.",
    "title": "La tierra de la sunamita",
    "references": "2 Reyes 8"
  },
  {
    "time": "841 a. C.",
    "title": "Jehú reina en Israel",
    "references": "2 Reyes 9"
  },
  {
    "time": "841 a. C.",
    "title": "Jehú mata a Joram",
    "references": "2 Reyes 9:11"
  },
  {
    "time": "841 a. C.",
    "title": "La familia de Ahab fue asesinada",
    "references": "2 Reyes 10"
  },
  {
    "time": "841 a. C.",
    "title": "Los adoradores de Baal asesinados",
    "references": "2 Reyes 10:18"
  },
  {
    "time": "841 a. C.",
    "title": "Joás escapa de Atalía",
    "references": "2 Reyes 11"
  },
  {
    "time": "841 a. C.",
    "title": "Ocozías sucede a Joram en Judá",
    "references": "2 Crónicas 22"
  },
  {
    "time": "841 a. C.",
    "title": "Joiada nombra rey a Joás",
    "references": "2 Crónicas 23"
  },
  {
    "time": "835 a. C.",
    "title": "Joás reina bien",
    "references": "2 Crónicas 24 , 2 Reyes 12"
  },
  {
    "time": "835 a. C.",
    "title": "La palabra del Señor a Joel",
    "references": "Joel 1-3"
  },
  {
    "time": "812 a. C.",
    "title": "Joás ordena reparaciones en el templo",
    "references": "2 Reyes 12:6"
  },
  {
    "time": "812 a. C.",
    "title": "El reinado malvado de Joacaz",
    "references": "2 Reyes 13"
  },
  {
    "time": "796 a. C.",
    "title": "El buen reinado de Amasías",
    "references": "2 Reyes 14 , 2 Crónicas 25"
  },
  {
    "time": "790 a. C.",
    "title": "El buen reinado de Azarías",
    "references": "2 Reyes 15"
  },
  {
    "time": "790 a. C.",
    "title": "Uzías reina en Judá",
    "references": "2 Crónicas 26"
  },
  {
    "time": "766 a. C.",
    "title": "Las palabras de Amós",
    "references": "Amós 1 - 9"
  },
  {
    "time": "760 a. C.",
    "title": "Jonás enviado a Nínive",
    "references": "Jonás 1 - 4"
  },
  {
    "time": "753 a. C.",
    "title": "Las profecías de Oseas",
    "references": "Oseas 1 - 14"
  },
  {
    "time": "750 a. C.",
    "title": "Jotam sucede a Uzías",
    "references": "2 Crónicas 27"
  },
  {
    "time": "742 a. C.",
    "title": "El malvado reinado de Acaz",
    "references": "2 Crónicas 28 , 2 Reyes 16"
  },
  {
    "time": "739 a. C.",
    "title": "Isaías se queja de la corrupción de Sión",
    "references": "Isaías 1 - 5"
  },
  {
    "time": "739 a. C.",
    "title": "La visión y la comisión de Isaías",
    "references": "Isaías 6"
  },
  {
    "time": "735 a. C.",
    "title": "La profecía de Isaías sobre Emanuel",
    "references": "Isaías 7"
  },
  {
    "time": "735 a. C.",
    "title": "La palabra del Señor a Miqueas",
    "references": "Miqueas 1 - 7"
  },
  {
    "time": "734 a. C.",
    "title": "Urías y Zacarías",
    "references": "Isaías 8"
  },
  {
    "time": "730 a. C.",
    "title": "Isaías profetiza que nacerá un niño",
    "references": "Isaías 9"
  },
  {
    "time": "730 a. C.",
    "title": "Isaías profetiza juicios sobre Israel",
    "references": "Isaías 9:8"
  },
  {
    "time": "730 a. C.",
    "title": "Isaías profetiza juicio sobre Asiria",
    "references": "Isaías 10"
  },
  {
    "time": "730 a. C.",
    "title": "Isaías profetiza la raíz de Jesé",
    "references": "Isaías 11"
  },
  {
    "time": "730 a. C.",
    "title": "La gozosa acción de gracias de Isaías",
    "references": "Isaías 12"
  },
  {
    "time": "725 a. C.",
    "title": "Isaías profetiza contra las naciones",
    "references": "Isaías 13 - 22"
  },
  {
    "time": "725 a. C.",
    "title": "El valle de la visión de Isaías",
    "references": "Isaías 22"
  },
  {
    "time": "725 a. C.",
    "title": "La carga de Isaías sobre Tiro",
    "references": "Isaías 23"
  },
  {
    "time": "725 a. C.",
    "title": "Devastación en la Tierra",
    "references": "Isaías 24"
  },
  {
    "time": "725 a. C.",
    "title": "Cantos de alabanza de Isaías",
    "references": "Isaías 25 - 27"
  },
  {
    "time": "725 a. C.",
    "title": "Otras advertencias de Isaías",
    "references": "Isaías 28 - 32"
  },
  {
    "time": "725 a. C.",
    "title": "Isaías profetiza que reinará un rey",
    "references": "Isaías 32"
  },
  {
    "time": "725 a. C.",
    "title": "Isaías declara los juicios de Dios",
    "references": "Isaías 33, 34"
  },
  {
    "time": "725 a. C.",
    "title": "Isaías declara que el gozo florecerá en Sión",
    "references": "Isaías 35"
  },
  {
    "time": "725 a. C.",
    "title": "Oseas el último rey de Israel",
    "references": "2 Reyes 17"
  },
  {
    "time": "722 a. C.",
    "title": "Israel llevado al cautiverio",
    "references": "2 Reyes 17:6"
  },
  {
    "time": "721 a. C.",
    "title": "Naciones extrañas trasplantadas a Samaria",
    "references": "2 Reyes 17:24"
  },
  {
    "time": "716 a. C.",
    "title": "El buen reinado de Ezequías",
    "references": "2 Crónicas 29"
  },
  {
    "time": "715 a. C.",
    "title": "Ezequías proclama una solemne Pascua",
    "references": "2 Crónicas 30"
  },
  {
    "time": "715 a. C.",
    "title": "La idolatría es destruida",
    "references": "2 Crónicas 31"
  },
  {
    "time": "712 a. C.",
    "title": "La enfermedad y la curación de Ezequías",
    "references": "2 Reyes 20 , Isaías 38"
  },
  {
    "time": "711 a. C.",
    "title": "Ezequías muestra tesoros",
    "references": "2 Reyes 20:12 , Isaías 39"
  },
  {
    "time": "711 a. C.",
    "title": "Isaías profetiza cautiverio y restauración",
    "references": "Isaías 40 - 66"
  },
  {
    "time": "701 a. C.",
    "title": "Senaquerib amenaza a Jerusalén",
    "references": "2 Reyes 18 , Isaías 36 , 2 Crónicas 32"
  },
  {
    "time": "701 a. C.",
    "title": "Salmos de refugio de Coré (2 Cr 32)",
    "references": "Salmos 46 - 48"
  },
  {
    "time": "701 a. C.",
    "title": "La oración de Ezequías",
    "references": "2 Reyes 19 , Isaías 37"
  },
  {
    "time": "697 a. C.",
    "title": "La visión de Nahum",
    "references": "Nahum 1 - 3"
  },
  {
    "time": "687 a. C.",
    "title": "El reinado perverso de Manasés",
    "references": "2 Reyes 21 , 2 Crónicas 33"
  },
  {
    "time": "640 a. C.",
    "title": "El buen reinado de Josías",
    "references": "2 Reyes 22 , 2 Crónicas 34"
  },
  {
    "time": "638 a. C.",
    "title": "La palabra del Señor a Sofonías",
    "references": "Sofonías 1 - 3"
  },
  {
    "time": "627 a. C.",
    "title": "El llamado de Jeremías",
    "references": "Jeremías 1"
  },
  {
    "time": "627 a. C.",
    "title": "Jeremías declara que Judá abandona a Dios",
    "references": "Jeremías 2 - 6"
  },
  {
    "time": "627 a. C.",
    "title": "El mensaje de Jeremías en la puerta del templo",
    "references": "Jeremías 7 - 10"
  },
  {
    "time": "625 a. C.",
    "title": "El Oráculo de Habacuc",
    "references": "Habacuc 1 - 3"
  },
  {
    "time": "622 a. C.",
    "title": "Jeremías proclama el pacto de Dios",
    "references": "Jeremías 11, 12"
  },
  {
    "time": "621 a. C.",
    "title": "Josías se prepara para la reparación del templo",
    "references": "2 Reyes 22:3"
  },
  {
    "time": "621 a. C.",
    "title": "Hilcías encuentra el libro perdido de la ley",
    "references": "2 Reyes 22:8"
  },
  {
    "time": "621 a. C.",
    "title": "Josías celebra la Pascua",
    "references": "2 Reyes 23 , 2 Crónicas 35"
  },
  {
    "time": "609 a. C.",
    "title": "El reinado malvado de Joacim.",
    "references": "2 Crónicas 36"
  },
  {
    "time": "609 a. C.",
    "title": "Jeremías proclama que el pacto está roto",
    "references": "Jeremías 13 - 20"
  },
  {
    "time": "609 a. C.",
    "title": "Jeremías profetiza contra Egipto",
    "references": "Jeremías 46"
  },
  {
    "time": "609 a. C.",
    "title": "Jeremías profetiza contra Filistea",
    "references": "Jeremías 47"
  },
  {
    "time": "605 a. C.",
    "title": "Daniel rechaza la porción del rey",
    "references": "Daniel 1"
  },
  {
    "time": "604 a. C.",
    "title": "Daniel interpreta el sueño de Nabucodonosor",
    "references": "Daniel 2"
  },
  {
    "time": "601 a. C.",
    "title": "Rebelión de Joacim",
    "references": "2 Reyes 24"
  },
  {
    "time": "597 a. C.",
    "title": "Joaquín exiliado",
    "references": "2 Reyes 24:10"
  },
  {
    "time": "597 a. C.",
    "title": "Sedequías reina en Judá",
    "references": "2 Reyes 24:18"
  },
  {
    "time": "594 a. C.",
    "title": "Jeremías profetiza contra Moab",
    "references": "Jeremías 48"
  },
  {
    "time": "594 a. C.",
    "title": "Jeremías profetiza contra Amón",
    "references": "Jeremías 49"
  },
  {
    "time": "593 a. C.",
    "title": "La profecía de Ezequiel en Quebar",
    "references": "Ezequiel 1"
  },
  {
    "time": "593 a. C.",
    "title": "El llamado y la instrucción de Ezequiel",
    "references": "Ezequiel 2"
  },
  {
    "time": "593 a. C.",
    "title": "Ezequiel come el rollo",
    "references": "Ezequiel 3"
  },
  {
    "time": "593 a. C.",
    "title": "Ezequiel predice el asedio de Jerusalén",
    "references": "Ezequiel 4, 5"
  },
  {
    "time": "593 a. C.",
    "title": "La visión de Ezequiel sobre el fin",
    "references": "Ezequiel 6, 7"
  },
  {
    "time": "592 a. C.",
    "title": "La visión del primer templo de Ezequiel",
    "references": "Ezequiel 8 - 19"
  },
  {
    "time": "591 a. C.",
    "title": "Ezequiel ve a Dios rechazar a los ancianos",
    "references": "Ezequiel 20"
  },
  {
    "time": "591 a. C.",
    "title": "Ezequiel profetiza contra Jerusalén",
    "references": "Ezequiel 21, 22"
  },
  {
    "time": "591 a. C.",
    "title": "Ezequiel profetiza contra dos hermanas",
    "references": "Ezequiel 23"
  },
  {
    "time": "588 a. C.",
    "title": "Comienza el asedio de Jerusalén",
    "references": "2 Reyes 25"
  },
  {
    "time": "588 a. C.",
    "title": "Los conflictos de Jeremías",
    "references": "Jeremías 21 - 33"
  },
  {
    "time": "588 a. C.",
    "title": "Jeremías profetiza juicio sobre Judá",
    "references": "Jeremías 34 - 45"
  },
  {
    "time": "588 a. C.",
    "title": "Comienza el asedio de Jerusalén",
    "references": "Ezequiel 24"
  },
  {
    "time": "587 a. C.",
    "title": "La venganza de Dios contra Amón y Edom",
    "references": "Ezequiel 25"
  },
  {
    "time": "586 a. C.",
    "title": "La caída de Jerusalén",
    "references": "2 Reyes 25 , Jeremías 52"
  },
  {
    "time": "586 a. C.",
    "title": "Salmos de desolación (Jer. 52)",
    "references": "Salmos 74, 79"
  },
  {
    "time": "586 a. C.",
    "title": "Jeremías profetiza contra Babilonia",
    "references": "Jeremías 50, 51"
  },
  {
    "time": "586 a. C.",
    "title": "Lamentaciones de Jeremías",
    "references": "Lamentaciones 1 - 5"
  },
  {
    "time": "586 a. C.",
    "title": "Ezequiel pronuncia juicio sobre Tiro",
    "references": "Ezequiel 26 - 28"
  },
  {
    "time": "586 a. C.",
    "title": "Ezequiel profetiza contra Egipto",
    "references": "Ezequiel 29 - 32"
  },
  {
    "time": "586 a. C.",
    "title": "Ezequiel el centinela",
    "references": "Ezequiel 33"
  },
  {
    "time": "585 a. C.",
    "title": "Ezequiel explica la caída de Jerusalén",
    "references": "Ezequiel 33:21"
  },
  {
    "time": "585 a. C.",
    "title": "Ezequiel prevé reprensión y restauración",
    "references": "Ezequiel 34 - 36"
  },
  {
    "time": "585 a. C.",
    "title": "Ezequiel ve la resurrección de los huesos secos",
    "references": "Ezequiel 37"
  },
  {
    "time": "585 a. C.",
    "title": "Ezequiel ve la batalla futura",
    "references": "Ezequiel 38"
  },
  {
    "time": "585 a. C.",
    "title": "Ezequiel ve el juicio de Dios sobre Gog",
    "references": "Ezequiel 39"
  },
  {
    "time": "585 a. C.",
    "title": "Sadrac, Mesac y Abednego",
    "references": "Daniel 3"
  },
  {
    "time": "582 a. C.",
    "title": "El sueño de Nabucodonosor",
    "references": "Daniel 4"
  },
  {
    "time": "582 a. C.",
    "title": "Daniel interpreta el sueño de Nabucodonosor",
    "references": "Daniel 4:19"
  },
  {
    "time": "573 a. C.",
    "title": "La visión del segundo templo de Ezequiel",
    "references": "Ezequiel 40 - 48"
  },
  {
    "time": "539 a. C.",
    "title": "Daniel interpreta la escritura en la pared",
    "references": "Daniel 5"
  },
  {
    "time": "539 a. C.",
    "title": "Daniel sobrevive al foso de los leones",
    "references": "Daniel 6"
  },
  {
    "time": "539 a. C.",
    "title": "La visión de Daniel sobre las cuatro bestias",
    "references": "Daniel 7"
  },
  {
    "time": "539 a. C.",
    "title": "La visión de Daniel del carnero y el macho cabrío",
    "references": "Daniel 8"
  },
  {
    "time": "539 a. C.",
    "title": "La oración de Daniel y la respuesta de Gabriel",
    "references": "Daniel 9"
  },
  {
    "time": "539 a. C.",
    "title": "Daniel consolado por el ángel",
    "references": "Daniel 10"
  },
  {
    "time": "539 a. C.",
    "title": "Daniel profetiza la caída de Persia",
    "references": "Daniel 11"
  },
  {
    "time": "539 a. C.",
    "title": "Daniel profetiza liberación para Israel",
    "references": "Daniel 12"
  },
  {
    "time": "537 a. C.",
    "title": "La proclamación de Ciro",
    "references": "Esdras 1"
  },
  {
    "time": "537 a. C.",
    "title": "Los exiliados regresan",
    "references": "Esdras 2"
  },
  {
    "time": "535 a. C.",
    "title": "Comienza la obra del templo",
    "references": "Esdras 3"
  },
  {
    "time": "534 a. C.",
    "title": "Los adversarios obstaculizan la obra del templo",
    "references": "Esdras 4"
  },
  {
    "time": "534 a. C.",
    "title": "Artajerjes ordena que se detengan las obras",
    "references": "Esdras 4:17"
  },
  {
    "time": "520 a. C.",
    "title": "Carta de Tattenai a Darío",
    "references": "Esdras 5"
  },
  {
    "time": "520 a. C.",
    "title": "La Palabra del Señor por Hageo",
    "references": "Hageo 1, 2"
  },
  {
    "time": "520 a. C.",
    "title": "La palabra del Señor a Zacarías",
    "references": "Zacarías 1 - 14"
  },
  {
    "time": "520 a. C.",
    "title": "La obra del templo se reanudó por decreto de Darío",
    "references": "Esdras 6"
  },
  {
    "time": "515 a. C.",
    "title": "Terminación y dedicación del templo",
    "references": "Esdras 6:16"
  },
  {
    "time": "483 a. C.",
    "title": "La reina Vasti destituida",
    "references": "Ester 1"
  },
  {
    "time": "478 a. C.",
    "title": "Ester se convierte en reina",
    "references": "Ester 2"
  },
  {
    "time": "478 a. C.",
    "title": "Mardoqueo frustra una conspiración",
    "references": "Ester 2:21"
  },
  {
    "time": "474 a. C.",
    "title": "Amán busca vengarse de los judíos",
    "references": "Ester 3"
  },
  {
    "time": "473 a. C.",
    "title": "Mardoqueo le informa a Ester sobre el complot de Amán",
    "references": "Ester 4"
  },
  {
    "time": "473 a. C.",
    "title": "Esther prepara un banquete",
    "references": "Ester 5"
  },
  {
    "time": "473 a. C.",
    "title": "El rey honra a Mardoqueo",
    "references": "Ester 6"
  },
  {
    "time": "473 a. C.",
    "title": "Amán es ahorcado",
    "references": "Ester 7"
  },
  {
    "time": "473 a. C.",
    "title": "Edicto de Jerjes en favor de Ester y los judíos",
    "references": "Ester 8"
  },
  {
    "time": "472 a. C.",
    "title": "Se instituyó Purim",
    "references": "Ester 9"
  },
  {
    "time": "472 a. C.",
    "title": "El tributo de Jerjes a Mardoqueo",
    "references": "Ester 10"
  },
  {
    "time": "458 a. C.",
    "title": "Esdras viaja a Jerusalén",
    "references": "Esdras 7"
  },
  {
    "time": "458 a. C.",
    "title": "Esdras encargado por Artajerjes",
    "references": "Esdras 7:11"
  },
  {
    "time": "457 a. C.",
    "title": "Las familias regresan a Jerusalén con Esdras",
    "references": "Esdras 8"
  },
  {
    "time": "457 a. C.",
    "title": "Las reformas de Esdras",
    "references": "Esdras 9"
  },
  {
    "time": "456 a. C.",
    "title": "La oración de Esdras sobre los matrimonios mixtos",
    "references": "Esdras 10"
  },
  {
    "time": "445 a. C.",
    "title": "La oración de Nehemías por los exiliados",
    "references": "Nehemías 1"
  },
  {
    "time": "444 a. C.",
    "title": "Artajerjes envía a Nehemías a Jerusalén",
    "references": "Nehemías 2"
  },
  {
    "time": "444 a. C.",
    "title": "Se nombran los constructores de los muros",
    "references": "Nehemías 3"
  },
  {
    "time": "444 a. C.",
    "title": "Los constructores superan el ridículo",
    "references": "Nehemías 4"
  },
  {
    "time": "444 a. C.",
    "title": "Nehemías elimina la deuda y la esclavitud",
    "references": "Nehemías 5"
  },
  {
    "time": "444 a. C.",
    "title": "El complot de Sanbalat",
    "references": "Nehemías 6"
  },
  {
    "time": "444 a. C.",
    "title": "Finalización del Muro",
    "references": "Nehemías 6:15"
  },
  {
    "time": "444 a. C.",
    "title": "Censo de exiliados retornados",
    "references": "Nehemías 7"
  },
  {
    "time": "444 a. C.",
    "title": "Esdras lee la ley",
    "references": "Nehemías 8"
  },
  {
    "time": "444 a. C.",
    "title": "Los israelitas ayunan y se arrepienten",
    "references": "Nehemías 9"
  },
  {
    "time": "444 a. C.",
    "title": "Los israelitas sellan el pacto",
    "references": "Nehemías 10"
  },
  {
    "time": "444 a. C.",
    "title": "La gente se establece en Jerusalén",
    "references": "Nehemías 11, 12"
  },
  {
    "time": "432 a. C.",
    "title": "Nehemías restaura las leyes",
    "references": "Nehemías 13"
  },
  {
    "time": "430 a. C.",
    "title": "La Palabra del Señor por Malaquías",
    "references": "Malaquías 1 - 4"
  }
]
